{"id":"an5.47","title":"AN 5.47 Dhana Sutta: Wealth","translator":"bodhi","text":"“Bhikkhus, there are these five kinds of wealth. What five? The wealth of faith, the wealth of virtuous behavior, the wealth of learning, the wealth of generosity, and the wealth of wisdom.\n\n(1) “And what, bhikkhus, is the wealth of faith? Here, a noble disciple is endowed with faith. He places faith in the enlightenment of the Tathāgata thus: ‘The Blessed One is an arahant, perfectly enlightened, accomplished in true knowledge and conduct, fortunate, knower of the world, unsurpassed trainer of persons to be tamed, teacher of devas and humans, the Enlightened One, the Blessed One.’ This is called the wealth of faith.\n\n(2) “And what is the wealth of virtuous behavior? Here, a noble disciple abstains from the destruction of life, abstains from taking what is not given, abstains from sexual misconduct, abstains from false speech, abstains from liquor, wine, and intoxicants, the basis for heedlessness. This is called the wealth of virtuous behavior.\n\n(3) “And what is the wealth of learning? Here, a noble disciple has learned much, remembers what he has learned, and accumulates what he has learned. Those teachings that are good in the beginning, good in the middle, and good in the end, with the right meaning and phrasing, which proclaim the perfectly complete and pure spiritual life—such teachings as these he has learned much of, retained in mind, recited verbally, mentally investigated, and penetrated well by view.\n\n(4) “And what is the wealth of generosity? Here, a noble disciple dwells at home with a heart devoid of the stain of miserliness, freely generous, openhanded, delighting in relinquishment, devoted to charity, delighting in giving and sharing. This is called the wealth of generosity.\n\n(5) “And what is the wealth of wisdom? Here, a noble disciple is wise; he possesses the wisdom that discerns arising and passing away, which is noble and penetrative and leads to the complete destruction of suffering. This is called the wealth of wisdom.\n\n“These, bhikkhus, are the five kinds of wealth.”\n\n> When one has faith in the Tathāgata,\n> \n> unshakable and well established,\n> \n> and virtuous behavior that is good,\n> \n> loved and praised by the noble ones;\n> \n> when one has confidence in the Saṅgha\n> \n> and one’s view has been straightened out,\n> \n> they say that one is not poor,\n> \n> that one’s life is not lived in vain.\n> Therefore an intelligent person,\n> \n> remembering the Buddhas’ teaching,\n> \n> should be intent on faith and virtuous behavior,\n> \n> confidence and vision of the Dhamma.\n\n© Bhikkhu Bodhi, The Numerical Discourses of the Buddha (Wisdom Publications, 2012)\nThis excerpt from The Numerical Discourses of the Buddha by Bhikkhu Bodhi is licensed under a Creative Commons Attribution-NonCommercial-NoDerivs 3.0 Unported License.\nBased on the work The Numerical Discourses of the Buddha at Wisdom Publications.\nPermissions beyond the scope of this license may be available at Wisdom Publications.\nPrepared for SuttaCentral by Blake Walsh.","description":"> … there are these five kinds of wealth. What five?\n\n<!---->","source":"suttacentral"}