{"id":"kp5","title":"Blessings","translator":"Bhikkhu Sujato","text":"## Blessings\n\nSo I have heard. At one time the Buddha was staying near Sāvatthī in Jeta’s Grove, Anāthapiṇḍika’s monastery. Then, late at night, a glorious deity, lighting up the entire Jeta’s Grove, went up to the Buddha, bowed, and stood to one side. That deity addressed the Buddha in verse:\n\n“Many gods and humans have thought about blessings desiring well-being: declare the highest blessing.”\n\n“Not to fraternize with fools, but to fraternize with the wise, and honoring those worthy of honor: this is the highest blessing.\n\nLiving in a suitable region, having made merit in the past, being rightly resolved in oneself, this is the highest blessing.\n\nEducation and a craft, discipline and training, and well-spoken speech: this is the highest blessing.\n\nCaring for mother and father, kindness to children and partners, and unstressful work: this is the highest blessing.\n\nGiving and righteous conduct, kindness to relatives, blameless deeds: this is the highest blessing.\n\nDesisting and abstaining from evil, avoiding drinking liquor, diligence in good qualities: this is the highest blessing.\n\nRespect and placidity, contentment and gratitude, and timely listening to the teaching: this is the highest blessing.\n\nPatience, being easy to admonish, the sight of ascetics, and timely discussion of the teaching: this is the highest blessing.\n\nFervor and chastity seeing the noble truths, and realization of extinguishment: this is the highest blessing.\n\nThough touched by worldly conditions, their mind does not tremble; sorrowless, stainless, secure: this is the highest blessing.\n\nHaving completed these things, undefeated everywhere; everywhere they go in safety: this is their highest blessing.”","description":"","source":"suttacentral-bilara"}