{"id":"sn35.166","title":"Giving Up Substantialist View","translator":"Bhikkhu Sujato","text":"## 16. The End of Relishing\n\nThen a mendicant went up to the Buddha … and said to him: “Sir, how does one know and see so that substantialist view is given up?” “Mendicant, knowing and seeing the eye, sights, eye consciousness, and eye contact as suffering, substantialist view is given up. … And also knowing and seeing the pleasant, painful, or neutral feeling that arises dependent on mind contact as suffering, substantialist view is given up. This is how to know and see so that substantialist view is given up.”","description":"","source":"suttacentral-bilara"}